gias3.examples-3.0.0-py3.9-nspkg.pth
gias3/examples/ASM_profile_matching.py
gias3/examples/HRV.py
gias3/examples/HRV_single_image_params_test.py
gias3/examples/STL_nearest_distance.py
gias3/examples/__init__.py
gias3/examples/csgcup.py
gias3/examples/hmf_inp_2_surf.py
gias3/examples/hmf_mat_map_inp.py
gias3/examples/inp_read_write.py
gias3/examples/inp_sample_dicom.py
gias3/examples/integral_image_cython.py
gias3/examples/modelio.py
gias3/examples/surface_to_surface_distance.py
gias3/examples/tetgen_meshes.py
gias3/examples/view_fieldwork_model_elements.py
gias3/examples/view_fieldwork_model_elements_script.py
gias3/examples/view_fieldwork_pca.py
gias3/examples/vtk_read_write.py
gias3/examples/data/2008_1741_tibia_fibula.wrl
gias3/examples/data/BN00104_E14727_S01_mc1 4_001.wrl
gias3/examples/data/autoCarpal1_outer.stl
gias3/examples/data/hip_test_image.npy
gias3/examples/data/manualCarpal1.stl
gias3/examples/data/prox_femur.inp
gias3/examples/data/prox_femur_out.inp
gias3/examples/data/tibia_left.ens
gias3/examples/data/tibia_left.geof
gias3/examples/data/tibia_left.mesh
gias3/examples/data/tibia_morphed.stl
gias3/examples/data/tibia_surface.stl
gias3/examples/data/tibia_volume.inp
gias3/examples/data/tetgen_mesh/femur_interior.1.edge
gias3/examples/data/tetgen_mesh/femur_interior.1.ele
gias3/examples/data/tetgen_mesh/femur_interior.1.face
gias3/examples/data/tetgen_mesh/femur_interior.1.node
gias3/examples/data/tetgen_mesh/femur_interior.1.smesh
gias3/examples/fieldwork/__init__.py
gias3/examples/fieldwork/build_2d_mesh.py
gias3/examples/fieldwork/fit_whole_pelvis.py
gias3/examples/fieldwork/host_mesh_fit_data.py
gias3/examples/fieldwork/host_mesh_fit_surface_data.py
gias3/examples/fieldwork/normalsmoother.py
gias3/examples/fieldwork/quartic_element_fitting.py
gias3/examples/fieldwork/quartic_elements.py
gias3/examples/fieldwork/remove_elements.py
gias3/examples/fieldwork/data/BN00104_E14727_S01_mc1 4_001.wrl
gias3.examples-3.0.0.dist-info/LICENSE
gias3.examples-3.0.0.dist-info/METADATA
gias3.examples-3.0.0.dist-info/WHEEL
gias3.examples-3.0.0.dist-info/namespace_packages.txt
gias3.examples-3.0.0.dist-info/top_level.txt
gias3.examples-3.0.0.dist-info/RECORD
